pywave/__init__.py
pywave/_data.py
pywave/_utils.py
pywave/wavfile.py
pywave/wavmanip.py
pywave/wavplay.py
wavpy-0.0.1.dist-info/LICENSE
wavpy-0.0.1.dist-info/METADATA
wavpy-0.0.1.dist-info/WHEEL
wavpy-0.0.1.dist-info/top_level.txt
wavpy-0.0.1.dist-info/RECORD
