Metadata-Version: 2.1
Name: wavpy
Version: 0.0.1
Summary: A package built to read, modify, play, and save WAV audio files.
Author-email: Leo Zhang <leozhang0214@gmail.com>
License: MIT License        
Project-URL: Homepage, https://github.com/leoz0214/pywave
Project-URL: Bug Tracker, https://github.com/leoz0214/pywave/issues
Classifier: Programming Language :: Python :: 3
Classifier: License :: OSI Approved :: MIT License
Requires-Python: >=3.9
License-File: LICENSE
